goblet/__init__.py
goblet/__version__.py
goblet/app.py
goblet/cli.py
goblet/client.py
goblet/common_cloud_actions.py
goblet/config.py
goblet/decorators.py
goblet/errors.py
goblet/globals.py
goblet/permissions.py
goblet/resource_manager.py
goblet/response.py
goblet/revision.py
goblet/test_utils.py
goblet/utils.py
goblet/write_files.py
goblet/alerts/__init__.py
goblet/alerts/alert_conditions.py
goblet/alerts/alerts.py
goblet/backends/__init__.py
goblet/backends/backend.py
goblet/backends/cloudfunctionv1.py
goblet/backends/cloudfunctionv2.py
goblet/backends/cloudrun.py
goblet/handlers/__init__.py
goblet/handlers/bq_remote_function.py
goblet/handlers/cloudtasktarget.py
goblet/handlers/eventarc.py
goblet/handlers/handler.py
goblet/handlers/http.py
goblet/handlers/jobs.py
goblet/handlers/pubsub.py
goblet/handlers/routes.py
goblet/handlers/scheduler.py
goblet/handlers/storage.py
goblet/handlers/uptime.py
goblet/handlers/plugins/__init__.py
goblet/handlers/plugins/pydantic.py
goblet/infrastructures/__init__.py
goblet/infrastructures/apigateway.py
goblet/infrastructures/bq_spark_stored_procedure.py
goblet/infrastructures/cloudtask.py
goblet/infrastructures/infrastructure.py
goblet/infrastructures/pubsub.py
goblet/infrastructures/redis.py
goblet/infrastructures/vpcconnector.py
goblet_gcp-0.14.0.dist-info/licenses/LICENSE
goblet_gcp-0.14.0.dist-info/METADATA
goblet_gcp-0.14.0.dist-info/WHEEL
goblet_gcp-0.14.0.dist-info/entry_points.txt
goblet_gcp-0.14.0.dist-info/top_level.txt
goblet_gcp-0.14.0.dist-info/RECORD
