Metadata-Version: 2.4
Name: goblet-gcp
Version: 0.14.0
Summary: Framework for writing serverless rest apis in python in google cloud.
Home-page: https://github.com/goblet/goblet
Author: Austen
Author-email: austen.novis@gmail.com
License: MIT
Classifier: License :: OSI Approved :: MIT License
Classifier: Programming Language :: Python
Classifier: Programming Language :: Python :: 3
Classifier: Programming Language :: Python :: 3.9
Classifier: Programming Language :: Python :: 3.10
Classifier: Programming Language :: Python :: 3.11
Classifier: Programming Language :: Python :: Implementation :: CPython
Classifier: Programming Language :: Python :: Implementation :: PyPy
Requires-Python: >=3.8.0
License-File: LICENSE
Requires-Dist: apispec
Requires-Dist: click
Requires-Dist: google-api-python-client
Requires-Dist: functions-framework
Requires-Dist: marshmallow
Requires-Dist: pydantic<3.0.0,>2.1.0
Requires-Dist: PyYAML
Requires-Dist: google-cloud-logging
Requires-Dist: google-cloud-appengine-logging
Requires-Dist: goblet-gcp-client
Dynamic: author
Dynamic: author-email
Dynamic: classifier
Dynamic: description
Dynamic: description-content-type
Dynamic: home-page
Dynamic: license
Dynamic: license-file
Dynamic: requires-dist
Dynamic: requires-python
Dynamic: summary
